{
  "706": {"surgery_types_mentioned": "none", "products_mentioned": "none", "treatments_mentioned": "none"},
  "707": {"products_mentioned": "none"},
  "708": {"conditions_mentioned": "none", "products_mentioned": "none"},
  "709": {"products_mentioned": "none"},
  "710": {"surgery_types_mentioned": "none", "products_mentioned": "none", "treatments_mentioned": "none"},
  "711": {"products_mentioned": "none"},
  "712": {"surgery_types_mentioned": "none"},
  "713": {"surgery_types_mentioned": "none", "products_mentioned": "none", "treatments_mentioned": "none"},
  "714": {"surgery_types_mentioned": "none", "products_mentioned": "none", "treatments_mentioned": "none"},
  "715": {"surgery_types_mentioned": "none", "products_mentioned": "none"},
  "717": {"products_mentioned": "none"},
  "718": {"surgery_types_mentioned": "none", "products_mentioned": "none", "treatments_mentioned": "none"},
  "719": {"surgery_types_mentioned": "none", "products_mentioned": "none", "treatments_mentioned": "none"},
  "720": {"surgery_types_mentioned": "nail removal", "products_mentioned": "none", "treatments_mentioned": "soaking, ketoconazole"},
  "721": {"products_mentioned": "none"},
  "722": {"conditions_mentioned": "none", "surgery_types_mentioned": "nail removal", "products_mentioned": "none"},
  "723": {"surgery_types_mentioned": "none", "products_mentioned": "none", "treatments_mentioned": "none"},
  "724": {"conditions_mentioned": "toenail infection, Raynaud's syndrome, wound", "products_mentioned": "none"},
  "726": {"surgery_types_mentioned": "none", "products_mentioned": "none"},
  "728": {"surgery_types_mentioned": "none", "products_mentioned": "Altra, heel cups"},
  "729": {"conditions_mentioned": "heel pain", "surgery_types_mentioned": "none"},
  "730": {"surgery_types_mentioned": "none"},
  "731": {"surgery_types_mentioned": "none", "products_mentioned": "heel pads"},
  "732": {"surgery_types_mentioned": "none"},
  "734": {"surgery_types_mentioned": "none"},
  "735": {"products_mentioned": "zinc oxide tape"},
  "736": {"surgery_types_mentioned": "none", "products_mentioned": "none", "treatments_mentioned": "none"},
  "737": {"surgery_types_mentioned": "none", "products_mentioned": "none", "treatments_mentioned": "none"},
  "738": {"surgery_types_mentioned": "none", "products_mentioned": "none"},
  "741": {"products_mentioned": "none"},
  "742": {"products_mentioned": "none"},
  "743": {"conditions_mentioned": "post-operative pain", "products_mentioned": "none"},
  "744": {"products_mentioned": "none"},
  "746": {"surgery_types_mentioned": "none"},
  "747": {"surgery_types_mentioned": "none", "products_mentioned": "none"},
  "748": {"surgery_types_mentioned": "none"},
  "750": {"products_mentioned": "none"},
  "751": {"surgery_types_mentioned": "bunionectomy", "products_mentioned": "none", "treatments_mentioned": "surgery"},
  "752": {"surgery_types_mentioned": "none", "products_mentioned": "none", "treatments_mentioned": "none"},
  "754": {"conditions_mentioned": "none", "products_mentioned": "none"}
}
